{
  "canonical_id": "jonny-b__wfc-3d-generator",
  "artifact": "add-on-wfc-3d-generator-v1.3.15.zip",
  "verify": {
    "3.6": {
      "state": "skipped_incompatible",
      "operators": [],
      "render_ok": false,
      "reason": "manifest extension needs Blender 4.2+ (no extension system on 3.6)"
    },
    "4.2": {
      "state": "partial",
      "operators": [
        "object.wfc_add_seed_list_item",
        "object.wfc_auto_generate_toggle",
        "object.wfc_auto_save_toggle",
        "object.wfc_cherry_picking",
        "object.wfc_copy_constraints_from_object",
        "object.wfc_export_json",
        "object.wfc_generate",
        "object.wfc_generic_add_list_item",
        "object.wfc_generic_duplicate_selected_items",
        "object.wfc_generic_order_down",
        "object.wfc_generic_order_up",
        "object.wfc_generic_remove_list_items",
        "object.wfc_get_selected_object",
        "object.wfc_import_json",
        "object.wfc_info_toggle",
        "object.wfc_list_invert_selection",
        "object.wfc_list_select_all",
        "object.wfc_list_select_none",
        "object.wfc_open_web_link",
        "object.wfc_random_seed",
        "object.wfc_remove_seed_list_items",
        "object.wfc_reset_all_constraints",
        "object.wfc_reset_constraints",
        "object.wfc_reset_render_result",
        "object.wfc_reset_search_result",
        "object.wfc_rotation",
        "object.wfc_rotation_get_selected_object",
        "object.wfc_rotation_select_dropdown_object",
        "object.wfc_save_active_constraints",
        "object.wfc_search",
        "object.wfc_select_dropdown_object",
        "object.wfc_set_props_to_default",
        "object.wfc_set_seed_direct",
        "object.wfc_stop_button",
        "object.wfc_target_collection_inc_number",
        "object.wfc_toggle_button",
        "object.wfc_toggle_hide_collection",
        "object.wfc_toggle_lines",
        "object.wfc_update_collection_list",
        "object.wfc_update_connector_constraints",
        "object.wfc_update_constraints",
        "object.wfc_update_grid_constraints",
        "object.wfc_update_neighbor_constraints",
        "object.wfc_validator",
        "object.wfc_validator_clear_log",
        "object.wfc_vis_directions"
      ],
      "render_ok": true
    },
    "4.5": {
      "state": "partial",
      "operators": [
        "object.wfc_add_seed_list_item",
        "object.wfc_auto_generate_toggle",
        "object.wfc_auto_save_toggle",
        "object.wfc_cherry_picking",
        "object.wfc_copy_constraints_from_object",
        "object.wfc_export_json",
        "object.wfc_generate",
        "object.wfc_generic_add_list_item",
        "object.wfc_generic_duplicate_selected_items",
        "object.wfc_generic_order_down",
        "object.wfc_generic_order_up",
        "object.wfc_generic_remove_list_items",
        "object.wfc_get_selected_object",
        "object.wfc_import_json",
        "object.wfc_info_toggle",
        "object.wfc_list_invert_selection",
        "object.wfc_list_select_all",
        "object.wfc_list_select_none",
        "object.wfc_open_web_link",
        "object.wfc_random_seed",
        "object.wfc_remove_seed_list_items",
        "object.wfc_reset_all_constraints",
        "object.wfc_reset_constraints",
        "object.wfc_reset_render_result",
        "object.wfc_reset_search_result",
        "object.wfc_rotation",
        "object.wfc_rotation_get_selected_object",
        "object.wfc_rotation_select_dropdown_object",
        "object.wfc_save_active_constraints",
        "object.wfc_search",
        "object.wfc_select_dropdown_object",
        "object.wfc_set_props_to_default",
        "object.wfc_set_seed_direct",
        "object.wfc_stop_button",
        "object.wfc_target_collection_inc_number",
        "object.wfc_toggle_button",
        "object.wfc_toggle_hide_collection",
        "object.wfc_toggle_lines",
        "object.wfc_update_collection_list",
        "object.wfc_update_connector_constraints",
        "object.wfc_update_constraints",
        "object.wfc_update_grid_constraints",
        "object.wfc_update_neighbor_constraints",
        "object.wfc_validator",
        "object.wfc_validator_clear_log",
        "object.wfc_vis_directions"
      ],
      "render_ok": true
    }
  },
  "operators": [
    "object.wfc_add_seed_list_item",
    "object.wfc_auto_generate_toggle",
    "object.wfc_auto_save_toggle",
    "object.wfc_cherry_picking",
    "object.wfc_copy_constraints_from_object",
    "object.wfc_export_json",
    "object.wfc_generate",
    "object.wfc_generic_add_list_item",
    "object.wfc_generic_duplicate_selected_items",
    "object.wfc_generic_order_down",
    "object.wfc_generic_order_up",
    "object.wfc_generic_remove_list_items",
    "object.wfc_get_selected_object",
    "object.wfc_import_json",
    "object.wfc_info_toggle",
    "object.wfc_list_invert_selection",
    "object.wfc_list_select_all",
    "object.wfc_list_select_none",
    "object.wfc_open_web_link",
    "object.wfc_random_seed",
    "object.wfc_remove_seed_list_items",
    "object.wfc_reset_all_constraints",
    "object.wfc_reset_constraints",
    "object.wfc_reset_render_result",
    "object.wfc_reset_search_result",
    "object.wfc_rotation",
    "object.wfc_rotation_get_selected_object",
    "object.wfc_rotation_select_dropdown_object",
    "object.wfc_save_active_constraints",
    "object.wfc_search",
    "object.wfc_select_dropdown_object",
    "object.wfc_set_props_to_default",
    "object.wfc_set_seed_direct",
    "object.wfc_stop_button",
    "object.wfc_target_collection_inc_number",
    "object.wfc_toggle_button",
    "object.wfc_toggle_hide_collection",
    "object.wfc_toggle_lines",
    "object.wfc_update_collection_list",
    "object.wfc_update_connector_constraints",
    "object.wfc_update_constraints",
    "object.wfc_update_grid_constraints",
    "object.wfc_update_neighbor_constraints",
    "object.wfc_validator",
    "object.wfc_validator_clear_log",
    "object.wfc_vis_directions"
  ],
  "prescan": "clean",
  "artifact_type": "extension_manifest",
  "verified_at": "2026-07-08T22:59:29+00:00",
  "prescan_hits": [
    "open-write"
  ],
  "declared_min": "4.2"
}